structlog_boilerplate
