Metadata-Version: 2.1
Name: structlog-boilerplate
Version: 0.2
Summary: Simple wrapper for CLI script which can use all advantages of structlog
Home-page: https://github.com/IaroslavR/structlog-boilerplate
Author: Iaroslav Russkikh
Author-email: iarruss@ya.ru
License: MIT
Platform: UNKNOWN
Classifier: Development Status :: 4 - Beta
Classifier: License :: OSI Approved :: MIT License
Classifier: Programming Language :: Python :: 3.6
